easyscan_server/__init__.py
easyscan_server/__main__.py
easyscan_server/domain.py
easyscan_server/main.py
easyscan_server/type.py
easyscan_server/templates/qrcode.html
easyscan_server-0.1.6.dist-info/METADATA
easyscan_server-0.1.6.dist-info/WHEEL
easyscan_server-0.1.6.dist-info/licenses/LICENSE
easyscan_server-0.1.6.dist-info/RECORD
