Metadata-Version: 2.4
Name: easyscan-server
Version: 0.1.6
Summary: EasyScan Server - A FastAPI-based server for EasyScan
License-File: LICENSE
Requires-Python: >=3.13
Requires-Dist: fakeredis>=2.30.1
Requires-Dist: fastapi[standard]>=0.115.12
Requires-Dist: redis>=6.2.0
Requires-Dist: textual>=3.5.0
Requires-Dist: uvicorn>=0.34.3
